[{"status":"failed","type":"waiver","metadata":{"notes":"This player was claimed by another owner."},"created":1758686562021,"settings":{"seq":11},"leg":3,"draft_picks":[],"creator":"217508316073422848","transaction_id":"1276427591619743744","adds":{"11638":8},"consenter_ids":[8],"drops":{"8148":8},"roster_ids":[8],"status_updated":1758697863309,"waiver_budget":[]},{"status":"failed","type":"waiver","metadata":{"notes":"This player was claimed by another owner."},"created":1758686379429,"settings":{"seq":10},"leg":3,"draft_picks":[],"creator":"217508316073422848","transaction_id":"1276426825773355008","adds":{"11589":8},"consenter_ids":[8],"drops":{"8148":8},"roster_ids":[8],"status_updated":1758697863309,"waiver_budget":[]},{"status":"complete","type":"waiver","metadata":{"notes":"Your waiver claim was processed successfully!"},"created":1758685773842,"settings":{"seq":2},"leg":3,"draft_picks":[],"creator":"1157703359105851392","transaction_id":"1276424285757386752","adds":{"11638":7},"consenter_ids":[7],"drops":{"7611":7},"roster_ids":[7],"status_updated":1758697863309,"waiver_budget":[]},{"status":"complete","type":"waiver","metadata":{"notes":"Your waiver claim was processed successfully!"},"created":1758683056375,"settings":{"seq":13},"leg":3,"draft_picks":[],"creator":"1157718631191642112","transaction_id":"1276412887874678784","adds":{"10917":5},"consenter_ids":[5],"drops":null,"roster_ids":[5],"status_updated":1758697863309,"waiver_budget":[]},{"status":"complete","type":"free_agent","metadata":null,"created":1758683034417,"settings":null,"leg":3,"draft_picks":[],"creator":"1157718631191642112","transaction_id":"1276412795771981825","adds":null,"consenter_ids":[5],"drops":{"12506":5},"roster_ids":[5],"status_updated":1758683034417,"waiver_budget":[]},{"status":"failed","type":"waiver","metadata":{"notes":"This player was claimed by another owner."},"created":1758682856075,"settings":{"seq":1},"leg":3,"draft_picks":[],"creator":"1157703359105851392","transaction_id":"1276412047755579392","adds":{"11589":7},"consenter_ids":[7],"drops":{"7611":7},"roster_ids":[7],"status_updated":1758697863309,"waiver_budget":[]},{"status":"failed","type":"waiver","metadata":{"notes":"This player was claimed by another owner."},"created":1758681942801,"settings":{"seq":12},"leg":3,"draft_picks":[],"creator":"1157718631191642112","transaction_id":"1276408217206816768","adds":{"11589":5},"consenter_ids":[5],"drops":null,"roster_ids":[5],"status_updated":1758697863309,"waiver_budget":[]},{"status":"complete","type":"waiver","metadata":{"notes":"Your waiver claim was processed successfully!"},"created":1758662396344,"settings":{"seq":18},"leg":3,"draft_picks":[],"creator":"1157053328455847936","transaction_id":"1276326233419808768","adds":{"11560":1},"consenter_ids":[1],"drops":{"5816":1},"roster_ids":[1],"status_updated":1758697863309,"waiver_budget":[]},{"status":"failed","type":"waiver","metadata":{"notes":"This player was claimed by another owner."},"created":1758658544865,"settings":{"priority":2,"seq":16},"leg":3,"draft_picks":[],"creator":"1157053328455847936","transaction_id":"1276310079150264320","adds":{"11638":1},"consenter_ids":[1],"drops":{"2449":1},"roster_ids":[1],"status_updated":1758697863309,"waiver_budget":[]},{"status":"failed","type":"waiver","metadata":{"notes":"This player was claimed by another owner."},"created":1758658520552,"settings":{"priority":1,"seq":15},"leg":3,"draft_picks":[],"creator":"1157053328455847936","transaction_id":"1276309977174130688","adds":{"11638":1},"consenter_ids":[1],"drops":{"5816":1},"roster_ids":[1],"status_updated":1758697863309,"waiver_budget":[]},{"status":"failed","type":"waiver","metadata":{"notes":"This player was claimed by another owner."},"created":1758657997040,"settings":{"priority":0,"seq":14},"leg":3,"draft_picks":[],"creator":"1157053328455847936","transaction_id":"1276307781405646848","adds":{"11589":1},"consenter_ids":[1],"drops":{"5816":1},"roster_ids":[1],"status_updated":1758697863309,"waiver_budget":[]},{"status":"failed","type":"waiver","metadata":{"notes":"This player was claimed by another owner."},"created":1758651382371,"settings":{"seq":21},"leg":3,"draft_picks":[],"creator":"1157700724621549568","transaction_id":"1276280037473021952","adds":{"10917":2},"consenter_ids":[2],"drops":{"2393":2},"roster_ids":[2],"status_updated":1758697863309,"waiver_budget":[]},{"status":"complete","type":"waiver","metadata":{"notes":"Your waiver claim was processed successfully!"},"created":1758651313460,"settings":{"seq":5},"leg":3,"draft_picks":[],"creator":"1157716283341869056","transaction_id":"1276279748439339008","adds":{"7525":3},"consenter_ids":[3],"drops":{"8136":3},"roster_ids":[3],"status_updated":1758697863309,"waiver_budget":[]},{"status":"complete","type":"waiver","metadata":{"notes":"Your waiver claim was processed successfully!"},"created":1758651300795,"settings":{"seq":6},"leg":3,"draft_picks":[],"creator":"1157700724621549568","transaction_id":"1276279695318478848","adds":{"6819":2},"consenter_ids":[2],"drops":{"11563":2},"roster_ids":[2],"status_updated":1758697863309,"waiver_budget":[]},{"status":"failed","type":"waiver","metadata":{"notes":"This player was claimed by another owner."},"created":1758644960803,"settings":{"seq":19},"leg":3,"draft_picks":[],"creator":"1157061020821696512","transaction_id":"1276253103464669184","adds":{"11638":6},"consenter_ids":[6],"drops":{"4983":6},"roster_ids":[6],"status_updated":1758697863309,"waiver_budget":[]},{"status":"complete","type":"waiver","metadata":{"notes":"Your waiver claim was processed successfully!"},"created":1758644879390,"settings":{"seq":0},"leg":3,"draft_picks":[],"creator":"1157061020821696512","transaction_id":"1276252761989578752","adds":{"11589":6},"consenter_ids":[6],"drops":{"4033":6},"roster_ids":[6],"status_updated":1758697863309,"waiver_budget":[]},{"status":"complete","type":"waiver","metadata":{"notes":"Your waiver claim was processed successfully!"},"created":1758625130882,"settings":{"seq":20},"leg":3,"draft_picks":[],"creator":"1255999161673715712","transaction_id":"1276169930747678720","adds":{"8289":4},"consenter_ids":[4],"drops":{"4135":4},"roster_ids":[4],"status_updated":1758697863309,"waiver_budget":[]},{"status":"complete","type":"waiver","metadata":{"notes":"Your waiver claim was processed successfully!"},"created":1758624994189,"settings":{"seq":3},"leg":3,"draft_picks":[],"creator":"1255999161673715712","transaction_id":"1276169357415698432","adds":{"10213":4},"consenter_ids":[4],"drops":{"12489":4},"roster_ids":[4],"status_updated":1758697863309,"waiver_budget":[]},{"status":"failed","type":"waiver","metadata":{"notes":"This player was claimed by another owner."},"created":1758622905527,"settings":{"priority":3,"seq":17},"leg":3,"draft_picks":[],"creator":"1157053328455847936","transaction_id":"1276160596928118784","adds":{"10917":1},"consenter_ids":[1],"drops":{"5816":1},"roster_ids":[1],"status_updated":1758697863309,"waiver_budget":[]},{"status":"failed","type":"waiver","metadata":{"notes":"This player was claimed by another owner."},"created":1758590744139,"settings":{"seq":9},"leg":3,"draft_picks":[],"creator":"217508316073422848","transaction_id":"1276025702289801217","adds":{"11589":8},"consenter_ids":[8],"drops":{"8148":8},"roster_ids":[8],"status_updated":1758697863309,"waiver_budget":[]},{"status":"failed","type":"waiver","metadata":{"notes":"This player was claimed by another owner."},"created":1758590726877,"settings":{"seq":8},"leg":3,"draft_picks":[],"creator":"217508316073422848","transaction_id":"1276025629891911680","adds":{"11638":8},"consenter_ids":[8],"drops":{"8148":8},"roster_ids":[8],"status_updated":1758697863309,"waiver_budget":[]},{"status":"failed","type":"waiver","metadata":{"notes":"This player was claimed by another owner."},"created":1758563057752,"settings":{"seq":7},"leg":3,"draft_picks":[],"creator":"217508316073422848","transaction_id":"1275909577170259968","adds":{"11589":8},"consenter_ids":[8],"drops":{"8148":8},"roster_ids":[8],"status_updated":1758697863309,"waiver_budget":[]},{"status":"failed","type":"waiver","metadata":{"notes":"This player was claimed by another owner."},"created":1758508426467,"settings":{"seq":4},"leg":3,"draft_picks":[],"creator":"1157716283341869056","transaction_id":"1275680436948848640","adds":{"11589":3},"consenter_ids":[3],"drops":{"8136":3},"roster_ids":[3],"status_updated":1758697863309,"waiver_budget":[]},{"status":"complete","type":"free_agent","metadata":null,"created":1758464397199,"settings":null,"leg":3,"draft_picks":[],"creator":"1157700724621549568","transaction_id":"1275495764818145280","adds":{"11563":2},"consenter_ids":[2],"drops":{"7525":2},"roster_ids":[2],"status_updated":1758464397199,"waiver_budget":[]},{"status":"complete","type":"free_agent","metadata":null,"created":1758453196299,"settings":null,"leg":3,"draft_picks":[],"creator":"1157703359105851392","transaction_id":"1275448784838492160","adds":{"5030":7},"consenter_ids":[7],"drops":{"10917":7},"roster_ids":[7],"status_updated":1758453196299,"waiver_budget":[]},{"status":"complete","type":"waiver","metadata":{"notes":"Your waiver claim was processed successfully!"},"created":1758252174833,"settings":{"seq":0},"leg":3,"draft_picks":[],"creator":"217508316073422848","transaction_id":"1274605639695355904","adds":{"9754":8},"consenter_ids":[8],"drops":{"11638":8},"roster_ids":[8],"status_updated":1758400283619,"waiver_budget":[]},{"status":"complete","type":"free_agent","metadata":null,"created":1758251669256,"settings":null,"leg":3,"draft_picks":[],"creator":"217508316073422848","transaction_id":"1274603519155929088","adds":{"8148":8},"consenter_ids":[8],"drops":{"11637":8},"roster_ids":[8],"status_updated":1758251669256,"waiver_budget":[]},{"status":"complete","type":"free_agent","metadata":null,"created":1758235047221,"settings":null,"leg":3,"draft_picks":[],"creator":"1157703359105851392","transaction_id":"1274533801288040448","adds":{"12481":7},"consenter_ids":[7],"drops":{"11563":7},"roster_ids":[7],"status_updated":1758235047221,"waiver_budget":[]},{"status":"complete","type":"free_agent","metadata":null,"created":1758230862035,"settings":null,"leg":3,"draft_picks":[],"creator":"1157716283341869056","transaction_id":"1274516247345635328","adds":{"6804":3},"consenter_ids":[3],"drops":{"9754":3},"roster_ids":[3],"status_updated":1758230862035,"waiver_budget":[]},{"status":"complete","type":"trade","metadata":null,"created":1758230498831,"settings":null,"leg":3,"draft_picks":[],"creator":"1157703359105851392","transaction_id":"1274514723957665792","adds":{"12526":3,"4984":7,"5850":3,"5927":3,"7543":7,"8112":7},"consenter_ids":[3,7],"drops":{"12526":7,"4984":3,"5850":7,"5927":7,"7543":3,"8112":3},"roster_ids":[3,7],"status_updated":1758234865269,"waiver_budget":[]},{"status":"failed","type":"waiver","metadata":{"notes":"This player was claimed by another owner."},"created":1758204561593,"settings":{"seq":1},"leg":3,"draft_picks":[],"creator":"1157703359105851392","transaction_id":"1274405935292375040","adds":{"8137":7},"consenter_ids":[7],"drops":{"11563":7},"roster_ids":[7],"status_updated":1758211271123,"waiver_budget":[]},{"status":"complete","type":"free_agent","metadata":null,"created":1758118087680,"settings":null,"leg":3,"draft_picks":[],"creator":"1157718631191642112","transaction_id":"1274043237417361408","adds":{"12506":5},"consenter_ids":[5],"drops":null,"roster_ids":[5],"status_updated":1758118087680,"waiver_budget":[]},{"status":"complete","type":"waiver","metadata":{"notes":"Your waiver claim was processed successfully!"},"created":1758117510495,"settings":{"seq":0},"leg":3,"draft_picks":[],"creator":"1157053328455847936","transaction_id":"1274040816528031745","adds":{"8137":1},"consenter_ids":[1],"drops":{"7553":1},"roster_ids":[1],"status_updated":1758211271123,"waiver_budget":[]},{"status":"complete","type":"free_agent","metadata":null,"created":1758117079066,"settings":null,"leg":3,"draft_picks":[],"creator":"1157053328455847936","transaction_id":"1274039006983618560","adds":{"1339":1},"consenter_ids":[1],"drops":{"4199":1},"roster_ids":[1],"status_updated":1758117079066,"waiver_budget":[]},{"status":"complete","type":"free_agent","metadata":null,"created":1758112163444,"settings":null,"leg":3,"draft_picks":[],"creator":"1157061020821696512","transaction_id":"1274018389370626048","adds":{"1052":6},"consenter_ids":[6],"drops":{"5726":6},"roster_ids":[6],"status_updated":1758112163444,"waiver_budget":[]},{"status":"complete","type":"free_agent","metadata":null,"created":1758112144868,"settings":null,"leg":3,"draft_picks":[],"creator":"1157061020821696512","transaction_id":"1274018311453036544","adds":{"5912":6},"consenter_ids":[6],"drops":{"11665":6},"roster_ids":[6],"status_updated":1758112144868,"waiver_budget":[]},{"status":"complete","type":"free_agent","metadata":null,"created":1758110462049,"settings":null,"leg":3,"draft_picks":[],"creator":"1157703359105851392","transaction_id":"1274011253202747392","adds":{"12185":7},"consenter_ids":[7],"drops":{"7839":7},"roster_ids":[7],"status_updated":1758110462049,"waiver_budget":[]},{"status":"complete","type":"free_agent","metadata":null,"created":1758110324433,"settings":null,"leg":3,"draft_picks":[],"creator":"1157703359105851392","transaction_id":"1274010675999416320","adds":{"7611":7},"consenter_ids":[7],"drops":{"11655":7},"roster_ids":[7],"status_updated":1758110324433,"waiver_budget":[]},{"status":"complete","type":"free_agent","metadata":null,"created":1758105523939,"settings":null,"leg":3,"draft_picks":[],"creator":"1157716283341869056","transaction_id":"1273990541264064512","adds":{"12499":3},"consenter_ids":[3],"drops":{"10236":3},"roster_ids":[3],"status_updated":1758105523939,"waiver_budget":[]}]